emojificate/__init__.py
emojificate/__main__.py
emojificate/_version.py
emojificate/defaults.py
emojificate/filter.py
emojificate/templatetags/__init__.py
emojificate/templatetags/emojificate.py
emojificate-0.7.0.dist-info/LICENSE
emojificate-0.7.0.dist-info/METADATA
emojificate-0.7.0.dist-info/WHEEL
emojificate-0.7.0.dist-info/top_level.txt
emojificate-0.7.0.dist-info/RECORD
