Metadata-Version: 2.1
Name: emojificate
Version: 0.7.0
Summary: Convert emoji in HTML to fallback images, alt text, title text, and aria labels.
Home-page: https://github.com/glasnt/emojificate
Author: Katie McLaughlin
Author-email: katie@glasnt.com
License: New BSD
Keywords: emoji accessibility a11y
Classifier: Development Status :: 3 - Alpha
Classifier: Environment :: Web Environment
Classifier: Intended Audience :: Developers
Classifier: License :: OSI Approved :: BSD License
Classifier: Operating System :: OS Independent
Classifier: Programming Language :: Python :: 3.7
Classifier: Programming Language :: Python :: 3.8
Classifier: Programming Language :: Python :: 3.9
Classifier: Programming Language :: Python :: 3.10
Classifier: Topic :: Text Processing :: Filters
Classifier: Topic :: Utilities
License-File: LICENSE
Requires-Dist: emoji
Requires-Dist: grapheme
Requires-Dist: requests
Requires-Dist: click
